{
  "symbol": "C",
  "name": "Citigroup Inc.",
  "current_price": 106.59,
  "pe_ratio": 15.248927,
  "forward_pe": 8.823675,
  "peg_ratio": null,
  "price_to_book": 0.9689472,
  "profit_margin": 0.18893999,
  "operating_margin": 0.25656998,
  "return_on_equity": 0.06831,
  "debt_to_equity": null,
  "fifty_two_week_high": 125.16,
  "fifty_two_week_low": 55.51,
  "three_month_average_volume": 14911720,
  "market_cap": 186459914240,
  "enterprise_value": -4458086912,
  "dividend_yield": 2.25,
  "dividend_rate": 2.4,
  "payout_ratio": 0.3319,
  "five_year_avg_dividend_yield": 3.46,
  "beta": 1.131,
  "sector": "Financial Services",
  "industry": "Banks - Diversified",
  "website": "https://www.citigroup.com",
  "description": "Citigroup Inc., a diversified financial service holding company, provides various financial products and services to consumers, corporations, governments, and institutions. It operates through five segments: Services, Markets, Banking, U.S. Personal Banking, and Wealth. The Services segment includes treasury and trade solutions, which provides cash management, trade, and working capital solutions to multinational corporations, financial institutions, and public sector organizations; and securities services, such as cross-border support for clients, local market expertise, post-trade technologies, data solutions, and various securities services solutions. The Markets segment offers sales and trading services for equities, foreign exchange, rates, spread products, and commodities to corporate, institutional, and public sector clients; and market-making services, including asset classes, risk management solutions, financing, and prime brokerage. The Banking segment includes investment banking services comprising equity and debt capital markets-related strategic financing solutions; advisory services related to mergers and acquisitions, divestitures, restructurings, and corporate defense activities; and corporate lending consists of corporate and commercial banking. The U.S. Personal Banking segment provides proprietary and co-branded card portfolios; and traditional banking services to retail and small business customers. The Wealth segment offers financial services to high-net-worth clients through banking, lending, mortgages, investment, custody, and trust product offerings; professional industries, including law firms, consulting groups, accounting, and asset management; and affluent and high net worth clients. The company operates in North America, the United Kingdom, Japan, North and South Asia, Australia, Europe, the Middle East, and Africa. Citigroup Inc. was founded in 1812 and is headquartered in New York, New York.",
  "previous_close": 106.53,
  "open_price": 104.45,
  "day_high": 107.05,
  "day_low": 102.0106,
  "fifty_day_average": 115.7538,
  "two_hundred_day_average": 100.0804,
  "stock_splits": null,
  "last_updated": "2026-03-10T10:10:46.312062",
  "historical_data": [
    {
      "date": "2025-12-10",
      "close": 111.08999633789062,
      "open": 109.36000061035156,
      "high": 111.91000366210938,
      "low": 109.26000213623047,
      "volume": 16584300
    },
    {
      "date": "2025-12-11",
      "close": 111.73999786376953,
      "open": 111.2699966430664,
      "high": 112.33999633789062,
      "low": 111.11000061035156,
      "volume": 10829700
    },
    {
      "date": "2025-12-12",
      "close": 111.80000305175781,
      "open": 113.30000305175781,
      "high": 113.43000030517578,
      "low": 111.19000244140625,
      "volume": 11227900
    },
    {
      "date": "2025-12-15",
      "close": 112.80000305175781,
      "open": 112.44999694824219,
      "high": 113.5199966430664,
      "low": 112.22000122070312,
      "volume": 10692100
    },
    {
      "date": "2025-12-16",
      "close": 111.27999877929688,
      "open": 112.80000305175781,
      "high": 113.37999725341797,
      "low": 110.55000305175781,
      "volume": 12418200
    },
    {
      "date": "2025-12-17",
      "close": 111.45999908447266,
      "open": 111.88999938964844,
      "high": 113.01000213623047,
      "low": 110.95999908447266,
      "volume": 9949700
    },
    {
      "date": "2025-12-18",
      "close": 112.83000183105469,
      "open": 112.22000122070312,
      "high": 113.8499984741211,
      "low": 112.12000274658203,
      "volume": 21155800
    },
    {
      "date": "2025-12-19",
      "close": 114.86000061035156,
      "open": 113.19999694824219,
      "high": 115.61000061035156,
      "low": 113.05000305175781,
      "volume": 37660800
    },
    {
      "date": "2025-12-22",
      "close": 118.08999633789062,
      "open": 115.20999908447266,
      "high": 118.6500015258789,
      "low": 114.87000274658203,
      "volume": 20178100
    },
    {
      "date": "2025-12-23",
      "close": 119.4000015258789,
      "open": 118.16000366210938,
      "high": 120.2699966430664,
      "low": 118.06999969482422,
      "volume": 16135000
    },
    {
      "date": "2025-12-24",
      "close": 121.55999755859375,
      "open": 119.70999908447266,
      "high": 122.83999633789062,
      "low": 119.25,
      "volume": 13529600
    },
    {
      "date": "2025-12-26",
      "close": 120.41999816894531,
      "open": 121.6500015258789,
      "high": 122.04000091552734,
      "low": 119.66999816894531,
      "volume": 10603700
    },
    {
      "date": "2025-12-29",
      "close": 118.12999725341797,
      "open": 120.36000061035156,
      "high": 120.56999969482422,
      "low": 117.9800033569336,
      "volume": 11000600
    },
    {
      "date": "2025-12-30",
      "close": 117.20999908447266,
      "open": 118.29000091552734,
      "high": 118.41000366210938,
      "low": 116.52999877929688,
      "volume": 8636100
    },
    {
      "date": "2025-12-31",
      "close": 116.69000244140625,
      "open": 117.4000015258789,
      "high": 117.62000274658203,
      "low": 116.37000274658203,
      "volume": 6203300
    },
    {
      "date": "2026-01-02",
      "close": 118.69999694824219,
      "open": 117.20999908447266,
      "high": 118.72000122070312,
      "low": 116.58999633789062,
      "volume": 9245400
    },
    {
      "date": "2026-01-05",
      "close": 123.30000305175781,
      "open": 119.30999755859375,
      "high": 124.0999984741211,
      "low": 119.30000305175781,
      "volume": 19993400
    },
    {
      "date": "2026-01-06",
      "close": 122.5,
      "open": 123.68000030517578,
      "high": 124.16999816894531,
      "low": 122.20999908447266,
      "volume": 11940100
    },
    {
      "date": "2026-01-07",
      "close": 121.37000274658203,
      "open": 122.30999755859375,
      "high": 122.58000183105469,
      "low": 120.69999694824219,
      "volume": 11595800
    },
    {
      "date": "2026-01-08",
      "close": 120.5999984741211,
      "open": 120.87999725341797,
      "high": 122.41999816894531,
      "low": 120.16000366210938,
      "volume": 14801500
    },
    {
      "date": "2026-01-09",
      "close": 121.31999969482422,
      "open": 120.94000244140625,
      "high": 121.73999786376953,
      "low": 120.1500015258789,
      "volume": 7565700
    },
    {
      "date": "2026-01-12",
      "close": 117.69999694824219,
      "open": 116.9000015258789,
      "high": 118.73999786376953,
      "low": 116.66999816894531,
      "volume": 19926900
    },
    {
      "date": "2026-01-13",
      "close": 116.30000305175781,
      "open": 117.72000122070312,
      "high": 118.2300033569336,
      "low": 115.54000091552734,
      "volume": 18332300
    },
    {
      "date": "2026-01-14",
      "close": 112.41000366210938,
      "open": 117.91000366210938,
      "high": 118.75,
      "low": 110.47000122070312,
      "volume": 27984600
    },
    {
      "date": "2026-01-15",
      "close": 117.45999908447266,
      "open": 113.8499984741211,
      "high": 117.95999908447266,
      "low": 112.75,
      "volume": 18719700
    },
    {
      "date": "2026-01-16",
      "close": 118.04000091552734,
      "open": 117.80000305175781,
      "high": 119.3499984741211,
      "low": 117.0,
      "volume": 17153800
    },
    {
      "date": "2026-01-20",
      "close": 112.80000305175781,
      "open": 114.45999908447266,
      "high": 116.5199966430664,
      "low": 112.38999938964844,
      "volume": 20451300
    },
    {
      "date": "2026-01-21",
      "close": 113.86000061035156,
      "open": 113.13999938964844,
      "high": 115.58999633789062,
      "low": 113.13999938964844,
      "volume": 14199900
    },
    {
      "date": "2026-01-22",
      "close": 115.66000366210938,
      "open": 114.56999969482422,
      "high": 116.63999938964844,
      "low": 114.05000305175781,
      "volume": 11271500
    },
    {
      "date": "2026-01-23",
      "close": 113.58999633789062,
      "open": 114.97000122070312,
      "high": 115.62999725341797,
      "low": 113.19999694824219,
      "volume": 12164400
    },
    {
      "date": "2026-01-26",
      "close": 114.81999969482422,
      "open": 113.9000015258789,
      "high": 115.4800033569336,
      "low": 113.86000061035156,
      "volume": 11728700
    },
    {
      "date": "2026-01-27",
      "close": 114.79000091552734,
      "open": 114.9000015258789,
      "high": 115.97000122070312,
      "low": 113.69999694824219,
      "volume": 11976800
    },
    {
      "date": "2026-01-28",
      "close": 114.19999694824219,
      "open": 114.5999984741211,
      "high": 115.70999908447266,
      "low": 113.13999938964844,
      "volume": 11378300
    },
    {
      "date": "2026-01-29",
      "close": 115.19999694824219,
      "open": 114.83999633789062,
      "high": 116.36000061035156,
      "low": 113.4000015258789,
      "volume": 14443200
    },
    {
      "date": "2026-01-30",
      "close": 115.70999908447266,
      "open": 114.41999816894531,
      "high": 116.6500015258789,
      "low": 114.18000030517578,
      "volume": 12396600
    },
    {
      "date": "2026-02-02",
      "close": 116.2300033569336,
      "open": 114.95999908447266,
      "high": 116.9800033569336,
      "low": 114.5999984741211,
      "volume": 11773700
    },
    {
      "date": "2026-02-03",
      "close": 117.70999908447266,
      "open": 117.0,
      "high": 118.91999816894531,
      "low": 115.37999725341797,
      "volume": 15332100
    },
    {
      "date": "2026-02-04",
      "close": 117.43000030517578,
      "open": 117.77999877929688,
      "high": 119.94000244140625,
      "low": 116.93000030517578,
      "volume": 12408300
    },
    {
      "date": "2026-02-05",
      "close": 115.73999786376953,
      "open": 116.41000366210938,
      "high": 116.41000366210938,
      "low": 112.91999816894531,
      "volume": 18704600
    },
    {
      "date": "2026-02-06",
      "close": 122.69000244140625,
      "open": 117.36000061035156,
      "high": 122.97000122070312,
      "low": 117.36000061035156,
      "volume": 15248800
    },
    {
      "date": "2026-02-09",
      "close": 123.7699966430664,
      "open": 122.19000244140625,
      "high": 125.16000366210938,
      "low": 121.69000244140625,
      "volume": 12887500
    },
    {
      "date": "2026-02-10",
      "close": 122.1500015258789,
      "open": 123.72000122070312,
      "high": 125.0,
      "low": 119.5,
      "volume": 12121300
    },
    {
      "date": "2026-02-11",
      "close": 117.38999938964844,
      "open": 123.58999633789062,
      "high": 124.23999786376953,
      "low": 117.36000061035156,
      "volume": 13771400
    },
    {
      "date": "2026-02-12",
      "close": 111.1500015258789,
      "open": 118.04000091552734,
      "high": 119.18000030517578,
      "low": 110.94000244140625,
      "volume": 19353300
    },
    {
      "date": "2026-02-13",
      "close": 110.86000061035156,
      "open": 109.7699966430664,
      "high": 111.43000030517578,
      "low": 108.38999938964844,
      "volume": 16665200
    },
    {
      "date": "2026-02-17",
      "close": 113.77999877929688,
      "open": 112.30000305175781,
      "high": 114.51000213623047,
      "low": 111.98999786376953,
      "volume": 12314600
    },
    {
      "date": "2026-02-18",
      "close": 116.2699966430664,
      "open": 115.04000091552734,
      "high": 117.04000091552734,
      "low": 114.97000122070312,
      "volume": 11678900
    },
    {
      "date": "2026-02-19",
      "close": 115.55000305175781,
      "open": 114.98999786376953,
      "high": 115.91000366210938,
      "low": 114.18000030517578,
      "volume": 8085300
    },
    {
      "date": "2026-02-20",
      "close": 116.0,
      "open": 115.26000213623047,
      "high": 116.12999725341797,
      "low": 113.83999633789062,
      "volume": 12986800
    },
    {
      "date": "2026-02-23",
      "close": 110.75,
      "open": 115.33999633789062,
      "high": 116.91000366210938,
      "low": 108.86000061035156,
      "volume": 17996400
    },
    {
      "date": "2026-02-24",
      "close": 109.55999755859375,
      "open": 109.44999694824219,
      "high": 111.4000015258789,
      "low": 107.5,
      "volume": 14981000
    },
    {
      "date": "2026-02-25",
      "close": 114.33999633789062,
      "open": 111.31999969482422,
      "high": 114.51000213623047,
      "low": 110.83000183105469,
      "volume": 13649100
    },
    {
      "date": "2026-02-26",
      "close": 116.19000244140625,
      "open": 114.69999694824219,
      "high": 117.0,
      "low": 114.45999908447266,
      "volume": 14759400
    },
    {
      "date": "2026-02-27",
      "close": 110.19000244140625,
      "open": 113.18000030517578,
      "high": 113.18000030517578,
      "low": 108.66000366210938,
      "volume": 29106900
    },
    {
      "date": "2026-03-02",
      "close": 111.44999694824219,
      "open": 106.26000213623047,
      "high": 111.88999938964844,
      "low": 106.19999694824219,
      "volume": 18976600
    },
    {
      "date": "2026-03-03",
      "close": 110.76000213623047,
      "open": 107.43000030517578,
      "high": 112.37999725341797,
      "low": 106.75,
      "volume": 15813300
    },
    {
      "date": "2026-03-04",
      "close": 111.31999969482422,
      "open": 111.66999816894531,
      "high": 112.33000183105469,
      "low": 110.48999786376953,
      "volume": 13042200
    },
    {
      "date": "2026-03-05",
      "close": 108.94999694824219,
      "open": 110.56999969482422,
      "high": 111.5999984741211,
      "low": 107.88999938964844,
      "volume": 15549100
    },
    {
      "date": "2026-03-06",
      "close": 106.52999877929688,
      "open": 105.19000244140625,
      "high": 106.58999633789062,
      "low": 103.08999633789062,
      "volume": 16586900
    },
    {
      "date": "2026-03-09",
      "close": 106.58999633789062,
      "open": 104.44999694824219,
      "high": 107.05000305175781,
      "low": 102.01000213623047,
      "volume": 18508300
    }
  ]
}